plain/start/CHANGELOG.md
plain/start/README.md
plain/start/__init__.py
plain/start/cli.py
plain_start-0.1.0.dist-info/METADATA
plain_start-0.1.0.dist-info/WHEEL
plain_start-0.1.0.dist-info/entry_points.txt
plain_start-0.1.0.dist-info/licenses/LICENSE
plain_start-0.1.0.dist-info/RECORD
