Metadata-Version: 2.4
Name: plain.start
Version: 0.1.0
Summary: Bootstrap a new Plain project from starter templates
Author-email: Dave Gaeddert <dave.gaeddert@dropseed.dev>
License-Expression: BSD-3-Clause
License-File: LICENSE
Requires-Python: >=3.13
Requires-Dist: click>=8.0.0
